odoo/addons/dms_auto_classification/README.rst
odoo/addons/dms_auto_classification/__init__.py
odoo/addons/dms_auto_classification/__manifest__.py
odoo/addons/dms_auto_classification/demo/dms_classification_template_demo.xml
odoo/addons/dms_auto_classification/i18n/dms_auto_classification.pot
odoo/addons/dms_auto_classification/i18n/es.po
odoo/addons/dms_auto_classification/i18n/it.po
odoo/addons/dms_auto_classification/i18n/sv.po
odoo/addons/dms_auto_classification/models/__init__.py
odoo/addons/dms_auto_classification/models/dms_classification_template.py
odoo/addons/dms_auto_classification/readme/CONFIGURE.md
odoo/addons/dms_auto_classification/readme/CONTRIBUTORS.md
odoo/addons/dms_auto_classification/readme/DESCRIPTION.md
odoo/addons/dms_auto_classification/readme/USAGE.md
odoo/addons/dms_auto_classification/security/ir.model.access.csv
odoo/addons/dms_auto_classification/security/security.xml
odoo/addons/dms_auto_classification/static/description/icon.png
odoo/addons/dms_auto_classification/static/description/icon.svg
odoo/addons/dms_auto_classification/static/description/index.html
odoo/addons/dms_auto_classification/tests/__init__.py
odoo/addons/dms_auto_classification/tests/test_dms_auto_classification.py
odoo/addons/dms_auto_classification/tests/data/test.zip
odoo/addons/dms_auto_classification/views/dms_classification_template_views.xml
odoo/addons/dms_auto_classification/wizards/__init__.py
odoo/addons/dms_auto_classification/wizards/wizard_dms_classification.py
odoo/addons/dms_auto_classification/wizards/wizard_dms_classification_views.xml
odoo_addon_dms_auto_classification-18.0.1.0.0.4.dist-info/METADATA
odoo_addon_dms_auto_classification-18.0.1.0.0.4.dist-info/WHEEL
odoo_addon_dms_auto_classification-18.0.1.0.0.4.dist-info/top_level.txt
odoo_addon_dms_auto_classification-18.0.1.0.0.4.dist-info/RECORD
